wwpdb/utils/align/SequenceExamples.py
wwpdb/utils/align/SequenceReferenceData.py
wwpdb/utils/align/__init__.py
wwpdb/utils/align/alignlib.cpython-313-x86_64-linux-gnu.so
wwpdb/utils/align/alignlib.pyi
wwpdb/utils/align/py.typed
wwpdb_utils_align-0.12.2.dist-info/METADATA
wwpdb_utils_align-0.12.2.dist-info/WHEEL
wwpdb_utils_align-0.12.2.dist-info/top_level.txt
wwpdb_utils_align-0.12.2.dist-info/RECORD
wwpdb_utils_align-0.12.2.dist-info/licenses/LICENSE
